boottorrent/__init__.py
boottorrent/boottorrent.py
boottorrent/cli.py
boottorrent/assets/README.rst
boottorrent/assets/ph1/bzImage
boottorrent/assets/ph1/diff.gz
boottorrent/assets/ph1/ldlinux.c32
boottorrent/assets/ph1/pxelinux.0
boottorrent/assets/ph1/pxelinux.cfg
boottorrent/assets/ph1/rootfs.gz
boottorrent/assets/skel/Boottorrent.yaml
boottorrent/assets/skel/README.rst
boottorrent/assets/skel/oss/README.rst
boottorrent/assets/tpls/aria2.conf.tpl
boottorrent/assets/tpls/dnsmasq.conf.tpl
boottorrent-0.1.1.dist-info/AUTHORS.rst
boottorrent-0.1.1.dist-info/LICENSE
boottorrent-0.1.1.dist-info/METADATA
boottorrent-0.1.1.dist-info/WHEEL
boottorrent-0.1.1.dist-info/entry_points.txt
boottorrent-0.1.1.dist-info/top_level.txt
boottorrent-0.1.1.dist-info/RECORD
