Metadata-Version: 2.1
Name: boottorrent
Version: 0.1.1
Summary: P2P bittorrent based network boot
Home-page: https://github.com/shreyanshk/boottorrent
Author: Shreyansh Khajanchi
Author-email: shreyansh_k@live.com
License: GNU General Public License v3
Keywords: boottorrent
Platform: UNKNOWN
Classifier: Development Status :: 2 - Pre-Alpha
Classifier: Intended Audience :: Developers
Classifier: License :: OSI Approved :: GNU General Public License v3 (GPLv3)
Classifier: Natural Language :: English
Classifier: Programming Language :: Python :: 3
Requires-Python: >=3.6
Requires-Dist: Jinja2 (>=2.10)
Requires-Dist: PyYAML (>=3.12)
